[
   {
      "Question Number": 1,
      "Difficulty": "Hard",
      "Rating": 73,
      "Question": "Who is the main character of Dr. Stone?",
      "Answer": "Dr. Stone"
   },
   {
      "Question Number": 2,
      "Difficulty": "Hard",
      "Rating": 78,
      "Question": "Who is the science user in the Kingdom of Science?",
      "Answer": "Senku Ishigami"
   },
   {
      "Question Number": 3,
      "Difficulty": "Easy",
      "Rating": 74,
      "Question": "What substance revived Senku from petrification?",
      "Answer": "Dr. Stone"
   },
   {
      "Question Number": 4,
      "Difficulty": "Hard",
      "Rating": 93,
      "Question": "What is Senku's primary field of expertise?",
      "Answer": "Senku Ishigami"
   },
   {
      "Question Number": 5,
      "Difficulty": "Easy",
      "Rating": 88,
      "Question": "What material does Senku use to make glass?",
      "Answer": "Senku Ishigami"
   },
   {
      "Question Number": 6,
      "Difficulty": "Easy",
      "Rating": 70,
      "Question": "Who is the leader of the Tsukasa Empire?",
      "Answer": "Dr. Stone"
   },
   {
      "Question Number": 7,
      "Difficulty": "Easy",
      "Rating": 77,
      "Question": "Who is the main antagonist at the start of the series?",
      "Answer": "Senku Ishigami"
   },
   {
      "Question Number": 8,
      "Difficulty": "Hard",
      "Rating": 70,
      "Question": "What is Senku's primary field of expertise?",
      "Answer": "Dr. Stone"
   },
   {
      "Question Number": 9,
      "Difficulty": "Easy",
      "Rating": 92,
      "Question": "What is Senku's primary field of expertise?",
      "Answer": "Senku Ishigami"
   },
   {
      "Question Number": 10,
      "Difficulty": "Medium",
      "Rating": 77,
      "Question": "What energy source does Senku aim to create?",
      "Answer": "Senku Ishigami"
   },
   {
      "Question Number": 11,
      "Difficulty": "Hard",
      "Rating": 78,
      "Question": "Who is the main character of Dr. Stone?",
      "Answer": "Dr. Stone"
   },
   {
      "Question Number": 12,
      "Difficulty": "Easy",
      "Rating": 92,
      "Question": "What material does Senku use to make glass?",
      "Answer": "Dr. Stone"
   },
   {
      "Question Number": 13,
      "Difficulty": "Medium",
      "Rating": 78,
      "Question": "Who is Senku's childhood friend?",
      "Answer": "Senku Ishigami"
   },
   {
      "Question Number": 14,
      "Difficulty": "Easy",
      "Rating": 100,
      "Question": "Who discovered the revival fluid in Dr. Stone?",
      "Answer": "Senku Ishigami"
   },
   {
      "Question Number": 15,
      "Difficulty": "Easy",
      "Rating": 72,
      "Question": "Who is the first person Senku revived?",
      "Answer": "Senku Ishigami"
   },
   {
      "Question Number": 16,
      "Difficulty": "Easy",
      "Rating": 81,
      "Question": "Which character is known for their strength in Dr. Stone?",
      "Answer": "Senku Ishigami"
   },
   {
      "Question Number": 17,
      "Difficulty": "Hard",
      "Rating": 78,
      "Question": "What is Senku's goal in Dr. Stone?",
      "Answer": "Dr. Stone"
   },
   {
      "Question Number": 18,
      "Difficulty": "Hard",
      "Rating": 84,
      "Question": "What is Senku's primary field of expertise?",
      "Answer": "Senku Ishigami"
   },
   {
      "Question Number": 19,
      "Difficulty": "Easy",
      "Rating": 99,
      "Question": "Who is the first person Senku revived?",
      "Answer": "Senku Ishigami"
   },
   {
      "Question Number": 20,
      "Difficulty": "Easy",
      "Rating": 87,
      "Question": "What is the name of the village Senku finds after awakening?",
      "Answer": "Dr. Stone"
   },
   {
      "Question Number": 21,
      "Difficulty": "Hard",
      "Rating": 89,
      "Question": "Which character is known for their strength in Dr. Stone?",
      "Answer": "Dr. Stone"
   },
   {
      "Question Number": 22,
      "Difficulty": "Hard",
      "Rating": 76,
      "Question": "Who is the leader of the Tsukasa Empire?",
      "Answer": "Senku Ishigami"
   },
   {
      "Question Number": 23,
      "Difficulty": "Easy",
      "Rating": 91,
      "Question": "Who is the science user in the Kingdom of Science?",
      "Answer": "Dr. Stone"
   },
   {
      "Question Number": 24,
      "Difficulty": "Medium",
      "Rating": 72,
      "Question": "Who is the science user in the Kingdom of Science?",
      "Answer": "Senku Ishigami"
   },
   {
      "Question Number": 25,
      "Difficulty": "Easy",
      "Rating": 82,
      "Question": "What is the name of Senku's father?",
      "Answer": "Senku Ishigami"
   },
   {
      "Question Number": 26,
      "Difficulty": "Medium",
      "Rating": 90,
      "Question": "Which character is known for their strength in Dr. Stone?",
      "Answer": "Dr. Stone"
   },
   {
      "Question Number": 27,
      "Difficulty": "Easy",
      "Rating": 81,
      "Question": "Which character is known for their strength in Dr. Stone?",
      "Answer": "Senku Ishigami"
   },
   {
      "Question Number": 28,
      "Difficulty": "Easy",
      "Rating": 91,
      "Question": "What is the name of Senku's father?",
      "Answer": "Dr. Stone"
   },
   {
      "Question Number": 29,
      "Difficulty": "Hard",
      "Rating": 99,
      "Question": "Who is the leader of the Tsukasa Empire?",
      "Answer": "Senku Ishigami"
   },
   {
      "Question Number": 30,
      "Difficulty": "Hard",
      "Rating": 90,
      "Question": "What year did the petrification event occur?",
      "Answer": "Senku Ishigami"
   },
   {
      "Question Number": 31,
      "Difficulty": "Hard",
      "Rating": 93,
      "Question": "Who is the science user in the Kingdom of Science?",
      "Answer": "Dr. Stone"
   },
   {
      "Question Number": 32,
      "Difficulty": "Easy",
      "Rating": 84,
      "Question": "Who is the first person Senku revived?",
      "Answer": "Dr. Stone"
   },
   {
      "Question Number": 33,
      "Difficulty": "Medium",
      "Rating": 99,
      "Question": "What is Senku's primary field of expertise?",
      "Answer": "Senku Ishigami"
   },
   {
      "Question Number": 34,
      "Difficulty": "Easy",
      "Rating": 91,
      "Question": "Who discovered the revival fluid in Dr. Stone?",
      "Answer": "Senku Ishigami"
   },
   {
      "Question Number": 35,
      "Difficulty": "Easy",
      "Rating": 77,
      "Question": "What is Senku's goal in Dr. Stone?",
      "Answer": "Senku Ishigami"
   },
   {
      "Question Number": 36,
      "Difficulty": "Medium",
      "Rating": 82,
      "Question": "What is the name of Senku's father?",
      "Answer": "Senku Ishigami"
   },
   {
      "Question Number": 37,
      "Difficulty": "Easy",
      "Rating": 76,
      "Question": "Who is the female lead alongside Senku?",
      "Answer": "Dr. Stone"
   },
   {
      "Question Number": 38,
      "Difficulty": "Hard",
      "Rating": 80,
      "Question": "What is the scientific tool Senku often uses?",
      "Answer": "Senku Ishigami"
   },
   {
      "Question Number": 39,
      "Difficulty": "Hard",
      "Rating": 85,
      "Question": "Who is the first person Senku revived?",
      "Answer": "Senku Ishigami"
   },
   {
      "Question Number": 40,
      "Difficulty": "Hard",
      "Rating": 84,
      "Question": "Who is Senku's childhood friend?",
      "Answer": "Dr. Stone"
   },
   {
      "Question Number": 41,
      "Difficulty": "Medium",
      "Rating": 74,
      "Question": "Who is the science user in the Kingdom of Science?",
      "Answer": "Dr. Stone"
   },
   {
      "Question Number": 42,
      "Difficulty": "Hard",
      "Rating": 87,
      "Question": "What is Senku's primary field of expertise?",
      "Answer": "Senku Ishigami"
   },
   {
      "Question Number": 43,
      "Difficulty": "Medium",
      "Rating": 93,
      "Question": "Who is the female lead alongside Senku?",
      "Answer": "Dr. Stone"
   },
   {
      "Question Number": 44,
      "Difficulty": "Medium",
      "Rating": 98,
      "Question": "Who is the female lead alongside Senku?",
      "Answer": "Senku Ishigami"
   },
   {
      "Question Number": 45,
      "Difficulty": "Medium",
      "Rating": 81,
      "Question": "Who is the science user in the Kingdom of Science?",
      "Answer": "Senku Ishigami"
   },
   {
      "Question Number": 46,
      "Difficulty": "Easy",
      "Rating": 86,
      "Question": "Who teaches Senku about survival techniques?",
      "Answer": "Dr. Stone"
   },
   {
      "Question Number": 47,
      "Difficulty": "Easy",
      "Rating": 94,
      "Question": "What is Senku's goal in Dr. Stone?",
      "Answer": "Senku Ishigami"
   },
   {
      "Question Number": 48,
      "Difficulty": "Easy",
      "Rating": 74,
      "Question": "What year did the petrification event occur?",
      "Answer": "Dr. Stone"
   },
   {
      "Question Number": 49,
      "Difficulty": "Hard",
      "Rating": 83,
      "Question": "What resource is crucial to the Kingdom of Science?",
      "Answer": "Senku Ishigami"
   },
   {
      "Question Number": 50,
      "Difficulty": "Easy",
      "Rating": 82,
      "Question": "Who is the first person Senku revived?",
      "Answer": "Senku Ishigami"
   },
   {
      "Question Number": 51,
      "Difficulty": "Hard",
      "Rating": 84,
      "Question": "Who is the main antagonist at the start of the series?",
      "Answer": "Dr. Stone"
   },
   {
      "Question Number": 52,
      "Difficulty": "Medium",
      "Rating": 87,
      "Question": "Who is the main character of Dr. Stone?",
      "Answer": "Dr. Stone"
   },
   {
      "Question Number": 53,
      "Difficulty": "Hard",
      "Rating": 93,
      "Question": "What substance revived Senku from petrification?",
      "Answer": "Senku Ishigami"
   },
   {
      "Question Number": 54,
      "Difficulty": "Hard",
      "Rating": 98,
      "Question": "What is Senku's primary field of expertise?",
      "Answer": "Senku Ishigami"
   },
   {
      "Question Number": 55,
      "Difficulty": "Medium",
      "Rating": 94,
      "Question": "Who discovered the revival fluid in Dr. Stone?",
      "Answer": "Senku Ishigami"
   },
   {
      "Question Number": 56,
      "Difficulty": "Easy",
      "Rating": 79,
      "Question": "What material does Senku use to make glass?",
      "Answer": "Senku Ishigami"
   },
   {
      "Question Number": 57,
      "Difficulty": "Easy",
      "Rating": 84,
      "Question": "Who is the main character of Dr. Stone?",
      "Answer": "Dr. Stone"
   },
   {
      "Question Number": 58,
      "Difficulty": "Hard",
      "Rating": 98,
      "Question": "What is the name of Senku's father?",
      "Answer": "Senku Ishigami"
   },
   {
      "Question Number": 59,
      "Difficulty": "Hard",
      "Rating": 94,
      "Question": "What year did the petrification event occur?",
      "Answer": "Senku Ishigami"
   },
   {
      "Question Number": 60,
      "Difficulty": "Hard",
      "Rating": 99,
      "Question": "What substance revived Senku from petrification?",
      "Answer": "Dr. Stone"
   },
   {
      "Question Number": 61,
      "Difficulty": "Hard",
      "Rating": 79,
      "Question": "Who is the main antagonist at the start of the series?",
      "Answer": "Dr. Stone"
   },
   {
      "Question Number": 62,
      "Difficulty": "Hard",
      "Rating": 76,
      "Question": "Who is Senku's childhood friend?",
      "Answer": "Senku Ishigami"
   },
   {
      "Question Number": 63,
      "Difficulty": "Medium",
      "Rating": 94,
      "Question": "What year did the petrification event occur?",
      "Answer": "Dr. Stone"
   },
   {
      "Question Number": 64,
      "Difficulty": "Hard",
      "Rating": 100,
      "Question": "Who is the main antagonist at the start of the series?",
      "Answer": "Senku Ishigami"
   },
   {
      "Question Number": 65,
      "Difficulty": "Easy",
      "Rating": 89,
      "Question": "Who discovered the revival fluid in Dr. Stone?",
      "Answer": "Senku Ishigami"
   },
   {
      "Question Number": 66,
      "Difficulty": "Medium",
      "Rating": 70,
      "Question": "What substance revived Senku from petrification?",
      "Answer": "Dr. Stone"
   },
   {
      "Question Number": 67,
      "Difficulty": "Medium",
      "Rating": 98,
      "Question": "What is the name of the village Senku finds after awakening?",
      "Answer": "Senku Ishigami"
   },
   {
      "Question Number": 68,
      "Difficulty": "Easy",
      "Rating": 71,
      "Question": "Who is the science user in the Kingdom of Science?",
      "Answer": "Dr. Stone"
   },
   {
      "Question Number": 69,
      "Difficulty": "Hard",
      "Rating": 100,
      "Question": "Who is the leader of the Tsukasa Empire?",
      "Answer": "Senku Ishigami"
   },
   {
      "Question Number": 70,
      "Difficulty": "Easy",
      "Rating": 93,
      "Question": "Who teaches Senku about survival techniques?",
      "Answer": "Senku Ishigami"
   },
   {
      "Question Number": 71,
      "Difficulty": "Easy",
      "Rating": 94,
      "Question": "What is Senku's primary field of expertise?",
      "Answer": "Dr. Stone"
   },
   {
      "Question Number": 72,
      "Difficulty": "Easy",
      "Rating": 74,
      "Question": "Who teaches Senku about survival techniques?",
      "Answer": "Dr. Stone"
   },
   {
      "Question Number": 73,
      "Difficulty": "Hard",
      "Rating": 75,
      "Question": "What is the name of Senku's father?",
      "Answer": "Senku Ishigami"
   },
   {
      "Question Number": 74,
      "Difficulty": "Hard",
      "Rating": 97,
      "Question": "What resource is crucial to the Kingdom of Science?",
      "Answer": "Senku Ishigami"
   },
   {
      "Question Number": 75,
      "Difficulty": "Medium",
      "Rating": 100,
      "Question": "What is the scientific tool Senku often uses?",
      "Answer": "Senku Ishigami"
   },
   {
      "Question Number": 76,
      "Difficulty": "Hard",
      "Rating": 94,
      "Question": "What is the scientific tool Senku often uses?",
      "Answer": "Senku Ishigami"
   },
   {
      "Question Number": 77,
      "Difficulty": "Hard",
      "Rating": 79,
      "Question": "Who is the first person Senku revived?",
      "Answer": "Dr. Stone"
   },
   {
      "Question Number": 78,
      "Difficulty": "Hard",
      "Rating": 90,
      "Question": "Which character is known for their strength in Dr. Stone?",
      "Answer": "Senku Ishigami"
   },
   {
      "Question Number": 79,
      "Difficulty": "Medium",
      "Rating": 98,
      "Question": "Who is the main antagonist at the start of the series?",
      "Answer": "Senku Ishigami"
   },
   {
      "Question Number": 80,
      "Difficulty": "Medium",
      "Rating": 73,
      "Question": "Who is the science user in the Kingdom of Science?",
      "Answer": "Dr. Stone"
   },
   {
      "Question Number": 81,
      "Difficulty": "Easy",
      "Rating": 72,
      "Question": "Who discovered the revival fluid in Dr. Stone?",
      "Answer": "Dr. Stone"
   },
   {
      "Question Number": 82,
      "Difficulty": "Easy",
      "Rating": 88,
      "Question": "What is Senku's primary field of expertise?",
      "Answer": "Senku Ishigami"
   },
   {
      "Question Number": 83,
      "Difficulty": "Easy",
      "Rating": 88,
      "Question": "Who is the science user in the Kingdom of Science?",
      "Answer": "Dr. Stone"
   },
   {
      "Question Number": 84,
      "Difficulty": "Easy",
      "Rating": 72,
      "Question": "What is Senku's goal in Dr. Stone?",
      "Answer": "Senku Ishigami"
   },
   {
      "Question Number": 85,
      "Difficulty": "Easy",
      "Rating": 72,
      "Question": "What is Senku's goal in Dr. Stone?",
      "Answer": "Senku Ishigami"
   },
   {
      "Question Number": 86,
      "Difficulty": "Medium",
      "Rating": 72,
      "Question": "Who is the main antagonist at the start of the series?",
      "Answer": "Dr. Stone"
   },
   {
      "Question Number": 87,
      "Difficulty": "Easy",
      "Rating": 78,
      "Question": "Who teaches Senku about survival techniques?",
      "Answer": "Senku Ishigami"
   },
   {
      "Question Number": 88,
      "Difficulty": "Easy",
      "Rating": 87,
      "Question": "Who is Senku's childhood friend?",
      "Answer": "Dr. Stone"
   },
   {
      "Question Number": 89,
      "Difficulty": "Hard",
      "Rating": 99,
      "Question": "Who is the female lead alongside Senku?",
      "Answer": "Senku Ishigami"
   },
   {
      "Question Number": 90,
      "Difficulty": "Hard",
      "Rating": 85,
      "Question": "Who is the science user in the Kingdom of Science?",
      "Answer": "Senku Ishigami"
   },
   {
      "Question Number": 91,
      "Difficulty": "Medium",
      "Rating": 95,
      "Question": "What material does Senku use to make glass?",
      "Answer": "Dr. Stone"
   },
   {
      "Question Number": 92,
      "Difficulty": "Easy",
      "Rating": 73,
      "Question": "What substance revived Senku from petrification?",
      "Answer": "Dr. Stone"
   },
   {
      "Question Number": 93,
      "Difficulty": "Hard",
      "Rating": 83,
      "Question": "Which character is known for their strength in Dr. Stone?",
      "Answer": "Senku Ishigami"
   },
   {
      "Question Number": 94,
      "Difficulty": "Medium",
      "Rating": 83,
      "Question": "What energy source does Senku aim to create?",
      "Answer": "Senku Ishigami"
   },
   {
      "Question Number": 95,
      "Difficulty": "Hard",
      "Rating": 71,
      "Question": "What substance revived Senku from petrification?",
      "Answer": "Senku Ishigami"
   },
   {
      "Question Number": 96,
      "Difficulty": "Easy",
      "Rating": 82,
      "Question": "Who discovered the revival fluid in Dr. Stone?",
      "Answer": "Senku Ishigami"
   },
   {
      "Question Number": 97,
      "Difficulty": "Easy",
      "Rating": 77,
      "Question": "What is the scientific tool Senku often uses?",
      "Answer": "Dr. Stone"
   },
   {
      "Question Number": 98,
      "Difficulty": "Easy",
      "Rating": 87,
      "Question": "What energy source does Senku aim to create?",
      "Answer": "Senku Ishigami"
   },
   {
      "Question Number": 99,
      "Difficulty": "Easy",
      "Rating": 83,
      "Question": "What year did the petrification event occur?",
      "Answer": "Senku Ishigami"
   },
   {
      "Question Number": 100,
      "Difficulty": "Medium",
      "Rating": 84,
      "Question": "Who is the science user in the Kingdom of Science?",
      "Answer": "Dr. Stone"
   },
   {
      "Question Number": 101,
      "Difficulty": "Easy",
      "Rating": 84,
      "Question": "What is Senku's primary field of expertise?",
      "Answer": "Dr. Stone"
   },
   {
      "Question Number": 102,
      "Difficulty": "Easy",
      "Rating": 71,
      "Question": "What is Senku's primary field of expertise?",
      "Answer": "Senku Ishigami"
   },
   {
      "Question Number": 103,
      "Difficulty": "Easy",
      "Rating": 72,
      "Question": "Who is the science user in the Kingdom of Science?",
      "Answer": "Dr. Stone"
   },
   {
      "Question Number": 104,
      "Difficulty": "Easy",
      "Rating": 83,
      "Question": "Who teaches Senku about survival techniques?",
      "Answer": "Senku Ishigami"
   },
   {
      "Question Number": 105,
      "Difficulty": "Medium",
      "Rating": 76,
      "Question": "Who is the first person Senku revived?",
      "Answer": "Senku Ishigami"
   },
   {
      "Question Number": 106,
      "Difficulty": "Easy",
      "Rating": 75,
      "Question": "Who is the first person Senku revived?",
      "Answer": "Dr. Stone"
   },
   {
      "Question Number": 107,
      "Difficulty": "Easy",
      "Rating": 82,
      "Question": "What is the name of Senku's father?",
      "Answer": "Senku Ishigami"
   },
   {
      "Question Number": 108,
      "Difficulty": "Medium",
      "Rating": 79,
      "Question": "What material does Senku use to make glass?",
      "Answer": "Dr. Stone"
   },
   {
      "Question Number": 109,
      "Difficulty": "Hard",
      "Rating": 100,
      "Question": "What is Senku's primary field of expertise?",
      "Answer": "Senku Ishigami"
   },
   {
      "Question Number": 110,
      "Difficulty": "Hard",
      "Rating": 92,
      "Question": "Who teaches Senku about survival techniques?",
      "Answer": "Senku Ishigami"
   },
   {
      "Question Number": 111,
      "Difficulty": "Easy",
      "Rating": 76,
      "Question": "What is the name of the village Senku finds after awakening?",
      "Answer": "Dr. Stone"
   },
   {
      "Question Number": 112,
      "Difficulty": "Easy",
      "Rating": 100,
      "Question": "What is Senku's goal in Dr. Stone?",
      "Answer": "Dr. Stone"
   },
   {
      "Question Number": 113,
      "Difficulty": "Hard",
      "Rating": 93,
      "Question": "What is Senku's primary field of expertise?",
      "Answer": "Senku Ishigami"
   },
   {
      "Question Number": 114,
      "Difficulty": "Easy",
      "Rating": 93,
      "Question": "Who discovered the revival fluid in Dr. Stone?",
      "Answer": "Senku Ishigami"
   },
   {
      "Question Number": 115,
      "Difficulty": "Easy",
      "Rating": 71,
      "Question": "Who is the female lead alongside Senku?",
      "Answer": "Senku Ishigami"
   },
   {
      "Question Number": 116,
      "Difficulty": "Medium",
      "Rating": 86,
      "Question": "Who is the main antagonist at the start of the series?",
      "Answer": "Senku Ishigami"
   },
   {
      "Question Number": 117,
      "Difficulty": "Easy",
      "Rating": 71,
      "Question": "Who is the main antagonist at the start of the series?",
      "Answer": "Dr. Stone"
   },
   {
      "Question Number": 118,
      "Difficulty": "Easy",
      "Rating": 97,
      "Question": "What year did the petrification event occur?",
      "Answer": "Senku Ishigami"
   },
   {
      "Question Number": 119,
      "Difficulty": "Easy",
      "Rating": 89,
      "Question": "Who is the leader of the Tsukasa Empire?",
      "Answer": "Senku Ishigami"
   },
   {
      "Question Number": 120,
      "Difficulty": "Hard",
      "Rating": 97,
      "Question": "Who is the science user in the Kingdom of Science?",
      "Answer": "Dr. Stone"
   },
   {
      "Question Number": 121,
      "Difficulty": "Medium",
      "Rating": 73,
      "Question": "Who is the female lead alongside Senku?",
      "Answer": "Dr. Stone"
   },
   {
      "Question Number": 122,
      "Difficulty": "Easy",
      "Rating": 88,
      "Question": "What resource is crucial to the Kingdom of Science?",
      "Answer": "Senku Ishigami"
   },
   {
      "Question Number": 123,
      "Difficulty": "Easy",
      "Rating": 89,
      "Question": "Who is the leader of the Tsukasa Empire?",
      "Answer": "Dr. Stone"
   },
   {
      "Question Number": 124,
      "Difficulty": "Medium",
      "Rating": 91,
      "Question": "Who is the female lead alongside Senku?",
      "Answer": "Senku Ishigami"
   },
   {
      "Question Number": 125,
      "Difficulty": "Hard",
      "Rating": 86,
      "Question": "Who discovered the revival fluid in Dr. Stone?",
      "Answer": "Senku Ishigami"
   },
   {
      "Question Number": 126,
      "Difficulty": "Medium",
      "Rating": 76,
      "Question": "Who discovered the revival fluid in Dr. Stone?",
      "Answer": "Dr. Stone"
   },
   {
      "Question Number": 127,
      "Difficulty": "Easy",
      "Rating": 78,
      "Question": "Who is the first person Senku revived?",
      "Answer": "Senku Ishigami"
   },
   {
      "Question Number": 128,
      "Difficulty": "Easy",
      "Rating": 91,
      "Question": "What is the name of the village Senku finds after awakening?",
      "Answer": "Dr. Stone"
   },
   {
      "Question Number": 129,
      "Difficulty": "Medium",
      "Rating": 80,
      "Question": "Who is the leader of the Tsukasa Empire?",
      "Answer": "Senku Ishigami"
   },
   {
      "Question Number": 130,
      "Difficulty": "Easy",
      "Rating": 84,
      "Question": "What resource is crucial to the Kingdom of Science?",
      "Answer": "Senku Ishigami"
   },
   {
      "Question Number": 131,
      "Difficulty": "Hard",
      "Rating": 73,
      "Question": "Who is the leader of the Tsukasa Empire?",
      "Answer": "Dr. Stone"
   },
   {
      "Question Number": 132,
      "Difficulty": "Hard",
      "Rating": 76,
      "Question": "Who is the main antagonist at the start of the series?",
      "Answer": "Dr. Stone"
   },
   {
      "Question Number": 133,
      "Difficulty": "Medium",
      "Rating": 74,
      "Question": "Which character is known for their strength in Dr. Stone?",
      "Answer": "Senku Ishigami"
   },
   {
      "Question Number": 134,
      "Difficulty": "Easy",
      "Rating": 98,
      "Question": "Who is the science user in the Kingdom of Science?",
      "Answer": "Senku Ishigami"
   },
   {
      "Question Number": 135,
      "Difficulty": "Medium",
      "Rating": 79,
      "Question": "What year did the petrification event occur?",
      "Answer": "Senku Ishigami"
   },
   {
      "Question Number": 136,
      "Difficulty": "Medium",
      "Rating": 96,
      "Question": "What is Senku's primary field of expertise?",
      "Answer": "Senku Ishigami"
   },
   {
      "Question Number": 137,
      "Difficulty": "Hard",
      "Rating": 79,
      "Question": "What resource is crucial to the Kingdom of Science?",
      "Answer": "Dr. Stone"
   },
   {
      "Question Number": 138,
      "Difficulty": "Hard",
      "Rating": 86,
      "Question": "Who is the main character of Dr. Stone?",
      "Answer": "Senku Ishigami"
   },
   {
      "Question Number": 139,
      "Difficulty": "Hard",
      "Rating": 96,
      "Question": "What is Senku's primary field of expertise?",
      "Answer": "Senku Ishigami"
   },
   {
      "Question Number": 140,
      "Difficulty": "Medium",
      "Rating": 99,
      "Question": "What substance revived Senku from petrification?",
      "Answer": "Dr. Stone"
   },
   {
      "Question Number": 141,
      "Difficulty": "Easy",
      "Rating": 78,
      "Question": "What substance revived Senku from petrification?",
      "Answer": "Dr. Stone"
   },
   {
      "Question Number": 142,
      "Difficulty": "Easy",
      "Rating": 93,
      "Question": "What is Senku's primary field of expertise?",
      "Answer": "Senku Ishigami"
   },
   {
      "Question Number": 143,
      "Difficulty": "Easy",
      "Rating": 78,
      "Question": "What is the name of the village Senku finds after awakening?",
      "Answer": "Dr. Stone"
   },
   {
      "Question Number": 144,
      "Difficulty": "Hard",
      "Rating": 76,
      "Question": "Who discovered the revival fluid in Dr. Stone?",
      "Answer": "Senku Ishigami"
   },
   {
      "Question Number": 145,
      "Difficulty": "Easy",
      "Rating": 91,
      "Question": "What is the name of Senku's father?",
      "Answer": "Senku Ishigami"
   },
   {
      "Question Number": 146,
      "Difficulty": "Hard",
      "Rating": 85,
      "Question": "What is the name of Senku's father?",
      "Answer": "Dr. Stone"
   },
   {
      "Question Number": 147,
      "Difficulty": "Easy",
      "Rating": 72,
      "Question": "What material does Senku use to make glass?",
      "Answer": "Senku Ishigami"
   },
   {
      "Question Number": 148,
      "Difficulty": "Medium",
      "Rating": 71,
      "Question": "Who is the main character of Dr. Stone?",
      "Answer": "Dr. Stone"
   },
   {
      "Question Number": 149,
      "Difficulty": "Medium",
      "Rating": 94,
      "Question": "Who is Senku's childhood friend?",
      "Answer": "Senku Ishigami"
   },
   {
      "Question Number": 150,
      "Difficulty": "Hard",
      "Rating": 78,
      "Question": "What year did the petrification event occur?",
      "Answer": "Senku Ishigami"
   },
   {
      "Question Number": 151,
      "Difficulty": "Hard",
      "Rating": 84,
      "Question": "What is Senku's primary field of expertise?",
      "Answer": "Dr. Stone"
   },
   {
      "Question Number": 152,
      "Difficulty": "Hard",
      "Rating": 83,
      "Question": "What is Senku's primary field of expertise?",
      "Answer": "Dr. Stone"
   },
   {
      "Question Number": 153,
      "Difficulty": "Easy",
      "Rating": 73,
      "Question": "Who is the leader of the Tsukasa Empire?",
      "Answer": "Senku Ishigami"
   },
   {
      "Question Number": 154,
      "Difficulty": "Hard",
      "Rating": 98,
      "Question": "Who is Senku's childhood friend?",
      "Answer": "Senku Ishigami"
   },
   {
      "Question Number": 155,
      "Difficulty": "Hard",
      "Rating": 71,
      "Question": "Which character is known for their strength in Dr. Stone?",
      "Answer": "Senku Ishigami"
   },
   {
      "Question Number": 156,
      "Difficulty": "Hard",
      "Rating": 87,
      "Question": "Who is Senku's childhood friend?",
      "Answer": "Senku Ishigami"
   },
   {
      "Question Number": 157,
      "Difficulty": "Medium",
      "Rating": 74,
      "Question": "What is Senku's goal in Dr. Stone?",
      "Answer": "Dr. Stone"
   },
   {
      "Question Number": 158,
      "Difficulty": "Medium",
      "Rating": 81,
      "Question": "What is Senku's goal in Dr. Stone?",
      "Answer": "Senku Ishigami"
   },
   {
      "Question Number": 159,
      "Difficulty": "Medium",
      "Rating": 76,
      "Question": "Who is the science user in the Kingdom of Science?",
      "Answer": "Senku Ishigami"
   },
   {
      "Question Number": 160,
      "Difficulty": "Hard",
      "Rating": 73,
      "Question": "Which character is known for their strength in Dr. Stone?",
      "Answer": "Dr. Stone"
   },
   {
      "Question Number": 161,
      "Difficulty": "Hard",
      "Rating": 98,
      "Question": "What material does Senku use to make glass?",
      "Answer": "Dr. Stone"
   },
   {
      "Question Number": 162,
      "Difficulty": "Hard",
      "Rating": 93,
      "Question": "Who is Senku's childhood friend?",
      "Answer": "Senku Ishigami"
   },
   {
      "Question Number": 163,
      "Difficulty": "Easy",
      "Rating": 97,
      "Question": "What year did the petrification event occur?",
      "Answer": "Dr. Stone"
   },
   {
      "Question Number": 164,
      "Difficulty": "Easy",
      "Rating": 98,
      "Question": "What material does Senku use to make glass?",
      "Answer": "Senku Ishigami"
   },
   {
      "Question Number": 165,
      "Difficulty": "Easy",
      "Rating": 75,
      "Question": "Who discovered the revival fluid in Dr. Stone?",
      "Answer": "Senku Ishigami"
   },
   {
      "Question Number": 166,
      "Difficulty": "Medium",
      "Rating": 95,
      "Question": "Who is the science user in the Kingdom of Science?",
      "Answer": "Dr. Stone"
   },
   {
      "Question Number": 167,
      "Difficulty": "Medium",
      "Rating": 75,
      "Question": "What substance revived Senku from petrification?",
      "Answer": "Senku Ishigami"
   },
   {
      "Question Number": 168,
      "Difficulty": "Medium",
      "Rating": 97,
      "Question": "What is Senku's goal in Dr. Stone?",
      "Answer": "Dr. Stone"
   },
   {
      "Question Number": 169,
      "Difficulty": "Medium",
      "Rating": 77,
      "Question": "What is the scientific tool Senku often uses?",
      "Answer": "Senku Ishigami"
   },
   {
      "Question Number": 170,
      "Difficulty": "Medium",
      "Rating": 81,
      "Question": "What is the name of the village Senku finds after awakening?",
      "Answer": "Senku Ishigami"
   },
   {
      "Question Number": 171,
      "Difficulty": "Easy",
      "Rating": 77,
      "Question": "Who is the main character of Dr. Stone?",
      "Answer": "Dr. Stone"
   },
   {
      "Question Number": 172,
      "Difficulty": "Hard",
      "Rating": 76,
      "Question": "Who is the first person Senku revived?",
      "Answer": "Dr. Stone"
   },
   {
      "Question Number": 173,
      "Difficulty": "Medium",
      "Rating": 78,
      "Question": "Who is the leader of the Tsukasa Empire?",
      "Answer": "Senku Ishigami"
   },
   {
      "Question Number": 174,
      "Difficulty": "Medium",
      "Rating": 81,
      "Question": "Who is the main antagonist at the start of the series?",
      "Answer": "Senku Ishigami"
   },
   {
      "Question Number": 175,
      "Difficulty": "Medium",
      "Rating": 91,
      "Question": "What is Senku's primary field of expertise?",
      "Answer": "Senku Ishigami"
   },
   {
      "Question Number": 176,
      "Difficulty": "Medium",
      "Rating": 100,
      "Question": "Who is the main character of Dr. Stone?",
      "Answer": "Senku Ishigami"
   },
   {
      "Question Number": 177,
      "Difficulty": "Easy",
      "Rating": 98,
      "Question": "What is the name of Senku's father?",
      "Answer": "Dr. Stone"
   },
   {
      "Question Number": 178,
      "Difficulty": "Easy",
      "Rating": 88,
      "Question": "What is the name of Senku's father?",
      "Answer": "Senku Ishigami"
   },
   {
      "Question Number": 179,
      "Difficulty": "Easy",
      "Rating": 73,
      "Question": "What resource is crucial to the Kingdom of Science?",
      "Answer": "Senku Ishigami"
   },
   {
      "Question Number": 180,
      "Difficulty": "Medium",
      "Rating": 81,
      "Question": "Who discovered the revival fluid in Dr. Stone?",
      "Answer": "Dr. Stone"
   },
   {
      "Question Number": 181,
      "Difficulty": "Medium",
      "Rating": 89,
      "Question": "Who is the main antagonist at the start of the series?",
      "Answer": "Dr. Stone"
   },
   {
      "Question Number": 182,
      "Difficulty": "Easy",
      "Rating": 82,
      "Question": "Who is the female lead alongside Senku?",
      "Answer": "Senku Ishigami"
   },
   {
      "Question Number": 183,
      "Difficulty": "Easy",
      "Rating": 78,
      "Question": "What is Senku's goal in Dr. Stone?",
      "Answer": "Dr. Stone"
   },
   {
      "Question Number": 184,
      "Difficulty": "Hard",
      "Rating": 83,
      "Question": "Who is the main character of Dr. Stone?",
      "Answer": "Senku Ishigami"
   },
   {
      "Question Number": 185,
      "Difficulty": "Hard",
      "Rating": 99,
      "Question": "What is Senku's primary field of expertise?",
      "Answer": "Senku Ishigami"
   },
   {
      "Question Number": 186,
      "Difficulty": "Hard",
      "Rating": 93,
      "Question": "What is the scientific tool Senku often uses?",
      "Answer": "Dr. Stone"
   },
   {
      "Question Number": 187,
      "Difficulty": "Medium",
      "Rating": 83,
      "Question": "Who is the leader of the Tsukasa Empire?",
      "Answer": "Senku Ishigami"
   },
   {
      "Question Number": 188,
      "Difficulty": "Hard",
      "Rating": 99,
      "Question": "Who discovered the revival fluid in Dr. Stone?",
      "Answer": "Dr. Stone"
   },
   {
      "Question Number": 189,
      "Difficulty": "Hard",
      "Rating": 80,
      "Question": "What substance revived Senku from petrification?",
      "Answer": "Senku Ishigami"
   },
   {
      "Question Number": 190,
      "Difficulty": "Hard",
      "Rating": 98,
      "Question": "What is the name of the village Senku finds after awakening?",
      "Answer": "Senku Ishigami"
   },
   {
      "Question Number": 191,
      "Difficulty": "Hard",
      "Rating": 79,
      "Question": "What material does Senku use to make glass?",
      "Answer": "Dr. Stone"
   },
   {
      "Question Number": 192,
      "Difficulty": "Medium",
      "Rating": 82,
      "Question": "What is the name of the village Senku finds after awakening?",
      "Answer": "Dr. Stone"
   },
   {
      "Question Number": 193,
      "Difficulty": "Hard",
      "Rating": 74,
      "Question": "What is the scientific tool Senku often uses?",
      "Answer": "Senku Ishigami"
   },
   {
      "Question Number": 194,
      "Difficulty": "Medium",
      "Rating": 91,
      "Question": "Who is the first person Senku revived?",
      "Answer": "Senku Ishigami"
   },
   {
      "Question Number": 195,
      "Difficulty": "Hard",
      "Rating": 93,
      "Question": "What year did the petrification event occur?",
      "Answer": "Senku Ishigami"
   },
   {
      "Question Number": 196,
      "Difficulty": "Hard",
      "Rating": 88,
      "Question": "What is the name of the village Senku finds after awakening?",
      "Answer": "Senku Ishigami"
   },
   {
      "Question Number": 197,
      "Difficulty": "Medium",
      "Rating": 87,
      "Question": "Who is the main character of Dr. Stone?",
      "Answer": "Dr. Stone"
   },
   {
      "Question Number": 198,
      "Difficulty": "Medium",
      "Rating": 79,
      "Question": "What is the scientific tool Senku often uses?",
      "Answer": "Senku Ishigami"
   },
   {
      "Question Number": 199,
      "Difficulty": "Medium",
      "Rating": 95,
      "Question": "Who is the female lead alongside Senku?",
      "Answer": "Senku Ishigami"
   },
   {
      "Question Number": 200,
      "Difficulty": "Hard",
      "Rating": 90,
      "Question": "Who discovered the revival fluid in Dr. Stone?",
      "Answer": "Dr. Stone"
   }
]